khidi/__init__.py
khidi/base_merchant_manager.py
khidi/everymatrix_merch_manager.py
khidi/merchant_factory.py
khidi/mima_merch_manager.py
khidi/schemas/__init__.py
khidi/schemas/everymatrix.py
khidi/schemas/mima.py
natura/__init__.py
natura/base_merchant_manager.py
natura/everymatrix_merch_manager.py
natura/merchant_factory.py
natura/mima_merch_manager.py
natura/schemas/__init__.py
natura/schemas/everymatrix.py
natura/schemas/mima.py
khidi-0.0.2.dist-info/METADATA
khidi-0.0.2.dist-info/WHEEL
khidi-0.0.2.dist-info/top_level.txt
khidi-0.0.2.dist-info/RECORD
