Metadata-Version: 2.1
Name: khidi
Version: 0.0.2
Author: MIMA GAMES
Author-email: 
License: MIT
Classifier: Programming Language :: Python :: 3.11
Requires-Python: >=3.11.0
Requires-Dist: pyhumps (==3.8.0)
Requires-Dist: requests (==2.28.1)
